cookiecutter_repo_extensions/__init__.py
cookiecutter_repo_extensions/repo_extensions.py
cookiecutter_repo_extensions-0.2.1.dist-info/DESCRIPTION.rst
cookiecutter_repo_extensions-0.2.1.dist-info/METADATA
cookiecutter_repo_extensions-0.2.1.dist-info/RECORD
cookiecutter_repo_extensions-0.2.1.dist-info/WHEEL
cookiecutter_repo_extensions-0.2.1.dist-info/metadata.json
cookiecutter_repo_extensions-0.2.1.dist-info/top_level.txt
