Metadata-Version: 2.0
Name: cookiecutter-repo-extensions
Version: 0.2.1
Summary: Hacky Jinja plugin that allows other jinja extensions to be loaded from the extensions directory of the repo
Home-page: https://github.com/ilsken/cookiecutter_repo_extensions
Author: Christopher Tarquini
Author-email: code@tarq.io
License: MIT license
Keywords: cookiecutter_repo_extensions
Platform: UNKNOWN
Classifier: Development Status :: 2 - Pre-Alpha
Classifier: Intended Audience :: Developers
Classifier: License :: OSI Approved :: MIT License
Classifier: Natural Language :: English
Classifier: Programming Language :: Python :: 2
Classifier: Programming Language :: Python :: 2.6
Classifier: Programming Language :: Python :: 2.7
Classifier: Programming Language :: Python :: 3
Classifier: Programming Language :: Python :: 3.3
Classifier: Programming Language :: Python :: 3.4
Classifier: Programming Language :: Python :: 3.5
